{
    "get": "players",
    "parameters": {
        "league": "141",
        "team": "718",
        "season": "2022",
        "page": "2"
    },
    "errors": [],
    "results": 20,
    "paging": {
        "current": 2,
        "total": 3
    },
    "response": [
        {
            "player": {
                "id": 46862,
                "name": "Borja S\u00e1nchez",
                "firstname": "Borja",
                "lastname": "S\u00e1nchez Laborde",
                "age": 27,
                "birth": {
                    "date": "1996-02-26",
                    "place": "Oviedo",
                    "country": "Spain"
                },
                "nationality": "Spain",
                "height": "185 cm",
                "weight": "80 kg",
                "injured": false,
                "photo": "https://media-3.api-sports.io/football/players/46862.png"
            },
            "statistics": [
                {
                    "team": {
                        "id": 718,
                        "name": "Oviedo",
                        "logo": "https://media-2.api-sports.io/football/teams/718.png"
                    },
                    "league": {
                        "id": 141,
                        "name": "Segunda Divisi\u00f3n",
                        "country": "Spain",
                        "logo": "https://media-2.api-sports.io/football/leagues/141.png",
                        "flag": "https://media-3.api-sports.io/flags/es.svg",
                        "season": 2022
                    },
                    "games": {
                        "appearences": 24,
                        "lineups": 12,
                        "minutes": 1205,
                        "number": null,
                        "position": "Midfielder",
                        "rating": "6.870833",
                        "captain": false
                    },
                    "substitutes": {
                        "in": 12,
                        "out": 11,
                        "bench": 15
                    },
                    "shots": {
                        "total": 12,
                        "on": 2
                    },
                    "goals": {
                        "total": 1,
                        "conceded": 0,
                        "assists": 2,
                        "saves": null
                    },
                    "passes": {
                        "total": 500,
                        "key": 17,
                        "accuracy": 16
                    },
                    "tackles": {
                        "total": 35,
                        "blocks": null,
                        "interceptions": 11
                    },
                    "duels": {
                        "total": 192,
                        "won": 101
                    },
                    "dribbles": {
                        "attempts": 49,
                        "success": 26,
                        "past": null
                    },
                    "fouls": {
                        "drawn": 26,
                        "committed": 20
                    },
                    "cards": {
                        "yellow": 3,
                        "yellowred": 0,
                        "red": 0
                    },
                    "penalty": {
                        "won": null,
                        "commited": null,
                        "scored": 0,
                        "missed": 0,
                        "saved": null
                    }
                }
            ]
        },
        {
            "player": {
                "id": 284061,
                "name": "M. Flores",
                "firstname": "Marcelo",
                "lastname": "Flores Dorrell",
                "age": 20,
                "birth": {
                    "date": "2003-10-01",
                    "place": null,
                    "country": "Mexico"
                },
                "nationality": "Mexico",
                "height": null,
                "weight": null,
                "injured": false,
                "photo": "https://media-1.api-sports.io/football/players/284061.png"
            },
            "statistics": [
                {
                    "team": {
                        "id": 718,
                        "name": "Oviedo",
                        "logo": "https://media-3.api-sports.io/football/teams/718.png"
                    },
                    "league": {
                        "id": 141,
                        "name": "Segunda Divisi\u00f3n",
                        "country": "Spain",
                        "logo": "https://media-2.api-sports.io/football/leagues/141.png",
                        "flag": "https://media-1.api-sports.io/flags/es.svg",
                        "season": 2022
                    },
                    "games": {
                        "appearences": 13,
                        "lineups": 7,
                        "minutes": 572,
                        "number": null,
                        "position": "Midfielder",
                        "rating": "6.553846",
                        "captain": false
                    },
                    "substitutes": {
                        "in": 6,
                        "out": 7,
                        "bench": 33
                    },
                    "shots": {
                        "total": 4,
                        "on": 2
                    },
                    "goals": {
                        "total": 0,
                        "conceded": 0,
                        "assists": 1,
                        "saves": null
                    },
                    "passes": {
                        "total": 169,
                        "key": 6,
                        "accuracy": 9
                    },
                    "tackles": {
                        "total": 10,
                        "blocks": 1,
                        "interceptions": 2
                    },
                    "duels": {
                        "total": 81,
                        "won": 34
                    },
                    "dribbles": {
                        "attempts": 28,
                        "success": 13,
                        "past": null
                    },
                    "fouls": {
                        "drawn": 6,
                        "committed": 9
                    },
                    "cards": {
                        "yellow": 0,
                        "yellowred": 0,
                        "red": 0
                    },
                    "penalty": {
                        "won": null,
                        "commited": null,
                        "scored": 0,
                        "missed": 0,
                        "saved": null
                    }
                }
            ]
        },
        {
            "player": {
                "id": 46863,
                "name": "Jimmy Su\u00e1rez",
                "firstname": "Jaime",
                "lastname": "Su\u00e1rez Juesas",
                "age": 27,
                "birth": {
                    "date": "1996-12-31",
                    "place": "Oviedo",
                    "country": "Spain"
                },
                "nationality": "Spain",
                "height": "170 cm",
                "weight": "68 kg",
                "injured": false,
                "photo": "https://media-3.api-sports.io/football/players/46863.png"
            },
            "statistics": [
                {
                    "team": {
                        "id": 718,
                        "name": "Oviedo",
                        "logo": "https://media-1.api-sports.io/football/teams/718.png"
                    },
                    "league": {
                        "id": 141,
                        "name": "Segunda Divisi\u00f3n",
                        "country": "Spain",
                        "logo": "https://media-2.api-sports.io/football/leagues/141.png",
                        "flag": "https://media-2.api-sports.io/flags/es.svg",
                        "season": 2022
                    },
                    "games": {
                        "appearences": 23,
                        "lineups": 18,
                        "minutes": 1497,
                        "number": null,
                        "position": "Midfielder",
                        "rating": "6.778260",
                        "captain": false
                    },
                    "substitutes": {
                        "in": 5,
                        "out": 7,
                        "bench": 10
                    },
                    "shots": {
                        "total": 6,
                        "on": 3
                    },
                    "goals": {
                        "total": 1,
                        "conceded": 0,
                        "assists": null,
                        "saves": null
                    },
                    "passes": {
                        "total": 554,
                        "key": 9,
                        "accuracy": 17
                    },
                    "tackles": {
                        "total": 36,
                        "blocks": 4,
                        "interceptions": 22
                    },
                    "duels": {
                        "total": 139,
                        "won": 76
                    },
                    "dribbles": {
                        "attempts": 7,
                        "success": 2,
                        "past": null
                    },
                    "fouls": {
                        "drawn": 17,
                        "committed": 16
                    },
                    "cards": {
                        "yellow": 5,
                        "yellowred": 0,
                        "red": 0
                    },
                    "penalty": {
                        "won": null,
                        "commited": null,
                        "scored": 0,
                        "missed": 0,
                        "saved": null
                    }
                }
            ]
        },
        {
            "player": {
                "id": 18998,
                "name": "Camarasa",
                "firstname": "V\u00edctor",
                "lastname": "Camarasa Ferrando",
                "age": 29,
                "birth": {
                    "date": "1994-05-28",
                    "place": "Meliana",
                    "country": "Spain"
                },
                "nationality": "Spain",
                "height": "183 cm",
                "weight": "76 kg",
                "injured": false,
                "photo": "https://media-1.api-sports.io/football/players/18998.png"
            },
            "statistics": [
                {
                    "team": {
                        "id": 718,
                        "name": "Oviedo",
                        "logo": "https://media-1.api-sports.io/football/teams/718.png"
                    },
                    "league": {
                        "id": 141,
                        "name": "Segunda Divisi\u00f3n",
                        "country": "Spain",
                        "logo": "https://media-3.api-sports.io/football/leagues/141.png",
                        "flag": "https://media-1.api-sports.io/flags/es.svg",
                        "season": 2022
                    },
                    "games": {
                        "appearences": 11,
                        "lineups": 6,
                        "minutes": 624,
                        "number": null,
                        "position": "Midfielder",
                        "rating": "6.718181",
                        "captain": false
                    },
                    "substitutes": {
                        "in": 5,
                        "out": 2,
                        "bench": 8
                    },
                    "shots": {
                        "total": 6,
                        "on": 1
                    },
                    "goals": {
                        "total": 0,
                        "conceded": 0,
                        "assists": 2,
                        "saves": null
                    },
                    "passes": {
                        "total": 351,
                        "key": 9,
                        "accuracy": 27
                    },
                    "tackles": {
                        "total": 6,
                        "blocks": null,
                        "interceptions": 10
                    },
                    "duels": {
                        "total": 73,
                        "won": 35
                    },
                    "dribbles": {
                        "attempts": 18,
                        "success": 8,
                        "past": null
                    },
                    "fouls": {
                        "drawn": 13,
                        "committed": 8
                    },
                    "cards": {
                        "yellow": 1,
                        "yellowred": 0,
                        "red": 0
                    },
                    "penalty": {
                        "won": null,
                        "commited": null,
                        "scored": 0,
                        "missed": 0,
                        "saved": null
                    }
                }
            ]
        },
        {
            "player": {
                "id": 6593,
                "name": "L. Sequeira",
                "firstname": "Leonardo Exequiel",
                "lastname": "Sequeira",
                "age": 28,
                "birth": {
                    "date": "1995-04-26",
                    "place": "La Banda",
                    "country": "Argentina"
                },
                "nationality": "Argentina",
                "height": "178 cm",
                "weight": null,
                "injured": false,
                "photo": "https://media-2.api-sports.io/football/players/6593.png"
            },
            "statistics": [
                {
                    "team": {
                        "id": 718,
                        "name": "Oviedo",
                        "logo": "https://media-3.api-sports.io/football/teams/718.png"
                    },
                    "league": {
                        "id": 141,
                        "name": "Segunda Divisi\u00f3n",
                        "country": "Spain",
                        "logo": "https://media-1.api-sports.io/football/leagues/141.png",
                        "flag": "https://media-1.api-sports.io/flags/es.svg",
                        "season": 2022
                    },
                    "games": {
                        "appearences": 12,
                        "lineups": 2,
                        "minutes": 269,
                        "number": null,
                        "position": "Midfielder",
                        "rating": "6.590909",
                        "captain": false
                    },
                    "substitutes": {
                        "in": 10,
                        "out": 3,
                        "bench": 13
                    },
                    "shots": {
                        "total": 3,
                        "on": 3
                    },
                    "goals": {
                        "total": 1,
                        "conceded": 0,
                        "assists": null,
                        "saves": null
                    },
                    "passes": {
                        "total": 53,
                        "key": 5,
                        "accuracy": 3
                    },
                    "tackles": {
                        "total": 5,
                        "blocks": null,
                        "interceptions": 2
                    },
                    "duels": {
                        "total": 81,
                        "won": 36
                    },
                    "dribbles": {
                        "attempts": 9,
                        "success": 2,
                        "past": null
                    },
                    "fouls": {
                        "drawn": 8,
                        "committed": 6
                    },
                    "cards": {
                        "yellow": 0,
                        "yellowred": 0,
                        "red": 0
                    },
                    "penalty": {
                        "won": null,
                        "commited": null,
                        "scored": 0,
                        "missed": 0,
                        "saved": null
                    }
                }
            ]
        },
        {
            "player": {
                "id": 161879,
                "name": "K. Koindredi",
                "firstname": "Koba Le\u00efn",
                "lastname": "Koindredi",
                "age": 22,
                "birth": {
                    "date": "2001-10-27",
                    "place": "Noum\u00e9a",
                    "country": "New Caledonia"
                },
                "nationality": "France",
                "height": "184 cm",
                "weight": null,
                "injured": false,
                "photo": "https://media-2.api-sports.io/football/players/161879.png"
            },
            "statistics": [
                {
                    "team": {
                        "id": 718,
                        "name": "Oviedo",
                        "logo": "https://media-3.api-sports.io/football/teams/718.png"
                    },
                    "league": {
                        "id": 141,
                        "name": "Segunda Divisi\u00f3n",
                        "country": "Spain",
                        "logo": "https://media-3.api-sports.io/football/leagues/141.png",
                        "flag": "https://media-1.api-sports.io/flags/es.svg",
                        "season": 2022
                    },
                    "games": {
                        "appearences": 18,
                        "lineups": 11,
                        "minutes": 927,
                        "number": null,
                        "position": "Midfielder",
                        "rating": "6.955555",
                        "captain": false
                    },
                    "substitutes": {
                        "in": 7,
                        "out": 11,
                        "bench": 15
                    },
                    "shots": {
                        "total": 8,
                        "on": 5
                    },
                    "goals": {
                        "total": 1,
                        "conceded": 0,
                        "assists": 2,
                        "saves": null
                    },
                    "passes": {
                        "total": 294,
                        "key": 12,
                        "accuracy": 12
                    },
                    "tackles": {
                        "total": 17,
                        "blocks": 1,
                        "interceptions": 7
                    },
                    "duels": {
                        "total": 165,
                        "won": 86
                    },
                    "dribbles": {
                        "attempts": 34,
                        "success": 19,
                        "past": null
                    },
                    "fouls": {
                        "drawn": 29,
                        "committed": 17
                    },
                    "cards": {
                        "yellow": 0,
                        "yellowred": 0,
                        "red": 0
                    },
                    "penalty": {
                        "won": null,
                        "commited": null,
                        "scored": 1,
                        "missed": 0,
                        "saved": null
                    }
                }
            ]
        },
        {
            "player": {
                "id": 46687,
                "name": "\u00c1ngel Montoro",
                "firstname": "\u00c1ngel",
                "lastname": "Montoro S\u00e1nchez",
                "age": 35,
                "birth": {
                    "date": "1988-06-25",
                    "place": "Valencia",
                    "country": "Spain"
                },
                "nationality": "Spain",
                "height": "181 cm",
                "weight": "72 kg",
                "injured": false,
                "photo": "https://media-3.api-sports.io/football/players/46687.png"
            },
            "statistics": [
                {
                    "team": {
                        "id": 718,
                        "name": "Oviedo",
                        "logo": "https://media-2.api-sports.io/football/teams/718.png"
                    },
                    "league": {
                        "id": 141,
                        "name": "Segunda Divisi\u00f3n",
                        "country": "Spain",
                        "logo": "https://media-3.api-sports.io/football/leagues/141.png",
                        "flag": "https://media-1.api-sports.io/flags/es.svg",
                        "season": 2022
                    },
                    "games": {
                        "appearences": 28,
                        "lineups": 15,
                        "minutes": 1667,
                        "number": null,
                        "position": "Midfielder",
                        "rating": "7.000000",
                        "captain": false
                    },
                    "substitutes": {
                        "in": 13,
                        "out": 9,
                        "bench": 14
                    },
                    "shots": {
                        "total": 11,
                        "on": 2
                    },
                    "goals": {
                        "total": 1,
                        "conceded": 0,
                        "assists": 1,
                        "saves": null
                    },
                    "passes": {
                        "total": 807,
                        "key": 22,
                        "accuracy": 22
                    },
                    "tackles": {
                        "total": 33,
                        "blocks": 4,
                        "interceptions": 17
                    },
                    "duels": {
                        "total": 156,
                        "won": 88
                    },
                    "dribbles": {
                        "attempts": 13,
                        "success": 8,
                        "past": null
                    },
                    "fouls": {
                        "drawn": 30,
                        "committed": 26
                    },
                    "cards": {
                        "yellow": 8,
                        "yellowred": 0,
                        "red": 0
                    },
                    "penalty": {
                        "won": null,
                        "commited": null,
                        "scored": 0,
                        "missed": 0,
                        "saved": null
                    }
                }
            ]
        },
        {
            "player": {
                "id": 107152,
                "name": "Hugo Rama",
                "firstname": "Hugo Jos\u00e9",
                "lastname": "Rama Calvi\u00f1o",
                "age": 27,
                "birth": {
                    "date": "1996-11-22",
                    "place": "Oroso",
                    "country": "Spain"
                },
                "nationality": "Spain",
                "height": "177 cm",
                "weight": "75 kg",
                "injured": false,
                "photo": "https://media-1.api-sports.io/football/players/107152.png"
            },
            "statistics": [
                {
                    "team": {
                        "id": 718,
                        "name": "Oviedo",
                        "logo": "https://media-3.api-sports.io/football/teams/718.png"
                    },
                    "league": {
                        "id": 141,
                        "name": "Segunda Divisi\u00f3n",
                        "country": "Spain",
                        "logo": "https://media-1.api-sports.io/football/leagues/141.png",
                        "flag": "https://media-1.api-sports.io/flags/es.svg",
                        "season": 2022
                    },
                    "games": {
                        "appearences": 34,
                        "lineups": 24,
                        "minutes": 1998,
                        "number": null,
                        "position": "Midfielder",
                        "rating": "6.703030",
                        "captain": false
                    },
                    "substitutes": {
                        "in": 10,
                        "out": 18,
                        "bench": 14
                    },
                    "shots": {
                        "total": 18,
                        "on": 7
                    },
                    "goals": {
                        "total": 0,
                        "conceded": 0,
                        "assists": 1,
                        "saves": null
                    },
                    "passes": {
                        "total": 733,
                        "key": 33,
                        "accuracy": 16
                    },
                    "tackles": {
                        "total": 41,
                        "blocks": null,
                        "interceptions": 11
                    },
                    "duels": {
                        "total": 234,
                        "won": 90
                    },
                    "dribbles": {
                        "attempts": 40,
                        "success": 17,
                        "past": null
                    },
                    "fouls": {
                        "drawn": 20,
                        "committed": 36
                    },
                    "cards": {
                        "yellow": 4,
                        "yellowred": 0,
                        "red": 0
                    },
                    "penalty": {
                        "won": null,
                        "commited": null,
                        "scored": 0,
                        "missed": 0,
                        "saved": null
                    }
                }
            ]
        },
        {
            "player": {
                "id": 286564,
                "name": "\u00c1lex Cardero",
                "firstname": "Alejandro",
                "lastname": "Su\u00e1rez Cardero",
                "age": 20,
                "birth": {
                    "date": "2003-08-25",
                    "place": "Oviedo",
                    "country": "Spain"
                },
                "nationality": "Spain",
                "height": null,
                "weight": null,
                "injured": false,
                "photo": "https://media-3.api-sports.io/football/players/286564.png"
            },
            "statistics": [
                {
                    "team": {
                        "id": 718,
                        "name": "Oviedo",
                        "logo": "https://media-3.api-sports.io/football/teams/718.png"
                    },
                    "league": {
                        "id": 141,
                        "name": "Segunda Divisi\u00f3n",
                        "country": "Spain",
                        "logo": "https://media-2.api-sports.io/football/leagues/141.png",
                        "flag": "https://media-3.api-sports.io/flags/es.svg",
                        "season": 2022
                    },
                    "games": {
                        "appearences": 0,
                        "lineups": 0,
                        "minutes": 0,
                        "number": null,
                        "position": "Midfielder",
                        "rating": null,
                        "captain": false
                    },
                    "substitutes": {
                        "in": 0,
                        "out": 0,
                        "bench": 2
                    },
                    "shots": {
                        "total": null,
                        "on": null
                    },
                    "goals": {
                        "total": 0,
                        "conceded": 0,
                        "assists": null,
                        "saves": null
                    },
                    "passes": {
                        "total": null,
                        "key": null,
                        "accuracy": null
                    },
                    "tackles": {
                        "total": null,
                        "blocks": null,
                        "interceptions": null
                    },
                    "duels": {
                        "total": null,
                        "won": null
                    },
                    "dribbles": {
                        "attempts": null,
                        "success": null,
                        "past": null
                    },
                    "fouls": {
                        "drawn": null,
                        "committed": null
                    },
                    "cards": {
                        "yellow": 0,
                        "yellowred": 0,
                        "red": 0
                    },
                    "penalty": {
                        "won": null,
                        "commited": null,
                        "scored": 0,
                        "missed": 0,
                        "saved": null
                    }
                }
            ]
        },
        {
            "player": {
                "id": 181259,
                "name": "Abel Bretones",
                "firstname": "Abel",
                "lastname": "Bretones Cruz",
                "age": 23,
                "birth": {
                    "date": "2000-08-21",
                    "place": "Langreo",
                    "country": "Spain"
                },
                "nationality": "Spain",
                "height": null,
                "weight": null,
                "injured": false,
                "photo": "https://media-1.api-sports.io/football/players/181259.png"
            },
            "statistics": [
                {
                    "team": {
                        "id": 718,
                        "name": "Oviedo",
                        "logo": "https://media-1.api-sports.io/football/teams/718.png"
                    },
                    "league": {
                        "id": 141,
                        "name": "Segunda Divisi\u00f3n",
                        "country": "Spain",
                        "logo": "https://media-3.api-sports.io/football/leagues/141.png",
                        "flag": "https://media-1.api-sports.io/flags/es.svg",
                        "season": 2022
                    },
                    "games": {
                        "appearences": 39,
                        "lineups": 31,
                        "minutes": 2877,
                        "number": null,
                        "position": "Midfielder",
                        "rating": "6.728205",
                        "captain": false
                    },
                    "substitutes": {
                        "in": 8,
                        "out": 6,
                        "bench": 9
                    },
                    "shots": {
                        "total": 20,
                        "on": 8
                    },
                    "goals": {
                        "total": 0,
                        "conceded": 0,
                        "assists": 2,
                        "saves": null
                    },
                    "passes": {
                        "total": 816,
                        "key": 25,
                        "accuracy": 12
                    },
                    "tackles": {
                        "total": 94,
                        "blocks": 6,
                        "interceptions": 23
                    },
                    "duels": {
                        "total": 396,
                        "won": 213
                    },
                    "dribbles": {
                        "attempts": 51,
                        "success": 24,
                        "past": null
                    },
                    "fouls": {
                        "drawn": 35,
                        "committed": 37
                    },
                    "cards": {
                        "yellow": 7,
                        "yellowred": 0,
                        "red": 0
                    },
                    "penalty": {
                        "won": null,
                        "commited": null,
                        "scored": 0,
                        "missed": 0,
                        "saved": null
                    }
                }
            ]
        },
        {
            "player": {
                "id": 193208,
                "name": "Mangel Prendes",
                "firstname": "Miguel \u00c1ngel",
                "lastname": "Prendes P\u00e9rez",
                "age": 22,
                "birth": {
                    "date": "2001-06-28",
                    "place": "Cand\u00e1s",
                    "country": "Spain"
                },
                "nationality": "Spain",
                "height": null,
                "weight": null,
                "injured": false,
                "photo": "https://media-1.api-sports.io/football/players/193208.png"
            },
            "statistics": [
                {
                    "team": {
                        "id": 718,
                        "name": "Oviedo",
                        "logo": "https://media-3.api-sports.io/football/teams/718.png"
                    },
                    "league": {
                        "id": 141,
                        "name": "Segunda Divisi\u00f3n",
                        "country": "Spain",
                        "logo": "https://media-2.api-sports.io/football/leagues/141.png",
                        "flag": "https://media-3.api-sports.io/flags/es.svg",
                        "season": 2022
                    },
                    "games": {
                        "appearences": 15,
                        "lineups": 5,
                        "minutes": 545,
                        "number": null,
                        "position": "Midfielder",
                        "rating": "6.576923",
                        "captain": false
                    },
                    "substitutes": {
                        "in": 10,
                        "out": 2,
                        "bench": 24
                    },
                    "shots": {
                        "total": 1,
                        "on": null
                    },
                    "goals": {
                        "total": 0,
                        "conceded": 0,
                        "assists": null,
                        "saves": null
                    },
                    "passes": {
                        "total": 226,
                        "key": 2,
                        "accuracy": 12
                    },
                    "tackles": {
                        "total": 12,
                        "blocks": null,
                        "interceptions": 4
                    },
                    "duels": {
                        "total": 78,
                        "won": 42
                    },
                    "dribbles": {
                        "attempts": 6,
                        "success": 2,
                        "past": null
                    },
                    "fouls": {
                        "drawn": 7,
                        "committed": 9
                    },
                    "cards": {
                        "yellow": 2,
                        "yellowred": 0,
                        "red": 0
                    },
                    "penalty": {
                        "won": null,
                        "commited": null,
                        "scored": 0,
                        "missed": 0,
                        "saved": null
                    }
                }
            ]
        },
        {
            "player": {
                "id": 333049,
                "name": "Yayo",
                "firstname": "Pelayo",
                "lastname": "Gonz\u00e1lez Rey",
                "age": 19,
                "birth": {
                    "date": "2004-07-30",
                    "place": "Oviedo",
                    "country": "Spain"
                },
                "nationality": "Spain",
                "height": null,
                "weight": null,
                "injured": false,
                "photo": "https://media-3.api-sports.io/football/players/333049.png"
            },
            "statistics": [
                {
                    "team": {
                        "id": 718,
                        "name": "Oviedo",
                        "logo": "https://media-2.api-sports.io/football/teams/718.png"
                    },
                    "league": {
                        "id": 141,
                        "name": "Segunda Divisi\u00f3n",
                        "country": "Spain",
                        "logo": "https://media-2.api-sports.io/football/leagues/141.png",
                        "flag": "https://media-2.api-sports.io/flags/es.svg",
                        "season": 2022
                    },
                    "games": {
                        "appearences": 3,
                        "lineups": 1,
                        "minutes": 69,
                        "number": null,
                        "position": "Midfielder",
                        "rating": "6.833333",
                        "captain": false
                    },
                    "substitutes": {
                        "in": 2,
                        "out": 1,
                        "bench": 8
                    },
                    "shots": {
                        "total": null,
                        "on": null
                    },
                    "goals": {
                        "total": 0,
                        "conceded": 0,
                        "assists": null,
                        "saves": null
                    },
                    "passes": {
                        "total": 27,
                        "key": 1,
                        "accuracy": 6
                    },
                    "tackles": {
                        "total": 4,
                        "blocks": null,
                        "interceptions": 3
                    },
                    "duels": {
                        "total": 5,
                        "won": 4
                    },
                    "dribbles": {
                        "attempts": null,
                        "success": null,
                        "past": null
                    },
                    "fouls": {
                        "drawn": null,
                        "committed": 1
                    },
                    "cards": {
                        "yellow": 0,
                        "yellowred": 0,
                        "red": 0
                    },
                    "penalty": {
                        "won": null,
                        "commited": null,
                        "scored": 0,
                        "missed": 0,
                        "saved": null
                    }
                }
            ]
        },
        {
            "player": {
                "id": 331344,
                "name": "V\u00edctor Blanco",
                "firstname": "V\u00edctor",
                "lastname": "Blanco S\u00e1nchez",
                "age": 21,
                "birth": {
                    "date": "2002-08-29",
                    "place": "Benidorm",
                    "country": "Spain"
                },
                "nationality": "Spain",
                "height": null,
                "weight": null,
                "injured": false,
                "photo": "https://media-2.api-sports.io/football/players/331344.png"
            },
            "statistics": [
                {
                    "team": {
                        "id": 718,
                        "name": "Oviedo",
                        "logo": "https://media-1.api-sports.io/football/teams/718.png"
                    },
                    "league": {
                        "id": 141,
                        "name": "Segunda Divisi\u00f3n",
                        "country": "Spain",
                        "logo": "https://media-1.api-sports.io/football/leagues/141.png",
                        "flag": "https://media-3.api-sports.io/flags/es.svg",
                        "season": 2022
                    },
                    "games": {
                        "appearences": 0,
                        "lineups": 0,
                        "minutes": 0,
                        "number": null,
                        "position": "Midfielder",
                        "rating": null,
                        "captain": false
                    },
                    "substitutes": {
                        "in": 0,
                        "out": 0,
                        "bench": 2
                    },
                    "shots": {
                        "total": null,
                        "on": null
                    },
                    "goals": {
                        "total": 0,
                        "conceded": 0,
                        "assists": null,
                        "saves": null
                    },
                    "passes": {
                        "total": null,
                        "key": null,
                        "accuracy": null
                    },
                    "tackles": {
                        "total": null,
                        "blocks": null,
                        "interceptions": null
                    },
                    "duels": {
                        "total": null,
                        "won": null
                    },
                    "dribbles": {
                        "attempts": null,
                        "success": null,
                        "past": null
                    },
                    "fouls": {
                        "drawn": null,
                        "committed": null
                    },
                    "cards": {
                        "yellow": 0,
                        "yellowred": 0,
                        "red": 0
                    },
                    "penalty": {
                        "won": null,
                        "commited": null,
                        "scored": 0,
                        "missed": 0,
                        "saved": null
                    }
                }
            ]
        },
        {
            "player": {
                "id": 46782,
                "name": "Manu Vallejo",
                "firstname": "Manuel Javier",
                "lastname": "Vallejo Galv\u00e1n",
                "age": 26,
                "birth": {
                    "date": "1997-02-14",
                    "place": "Chiclana de la Frontera",
                    "country": "Spain"
                },
                "nationality": "Spain",
                "height": "167 cm",
                "weight": "72 kg",
                "injured": false,
                "photo": "https://media-1.api-sports.io/football/players/46782.png"
            },
            "statistics": [
                {
                    "team": {
                        "id": 718,
                        "name": "Oviedo",
                        "logo": "https://media-2.api-sports.io/football/teams/718.png"
                    },
                    "league": {
                        "id": 141,
                        "name": "Segunda Divisi\u00f3n",
                        "country": "Spain",
                        "logo": "https://media-3.api-sports.io/football/leagues/141.png",
                        "flag": "https://media-2.api-sports.io/flags/es.svg",
                        "season": 2022
                    },
                    "games": {
                        "appearences": 16,
                        "lineups": 9,
                        "minutes": 790,
                        "number": null,
                        "position": "Attacker",
                        "rating": "6.773333",
                        "captain": false
                    },
                    "substitutes": {
                        "in": 7,
                        "out": 8,
                        "bench": 9
                    },
                    "shots": {
                        "total": 12,
                        "on": 5
                    },
                    "goals": {
                        "total": 4,
                        "conceded": 0,
                        "assists": null,
                        "saves": null
                    },
                    "passes": {
                        "total": 157,
                        "key": 7,
                        "accuracy": 8
                    },
                    "tackles": {
                        "total": 10,
                        "blocks": null,
                        "interceptions": 3
                    },
                    "duels": {
                        "total": 112,
                        "won": 46
                    },
                    "dribbles": {
                        "attempts": 11,
                        "success": 6,
                        "past": null
                    },
                    "fouls": {
                        "drawn": 15,
                        "committed": 10
                    },
                    "cards": {
                        "yellow": 1,
                        "yellowred": 0,
                        "red": 0
                    },
                    "penalty": {
                        "won": null,
                        "commited": null,
                        "scored": 1,
                        "missed": 0,
                        "saved": null
                    }
                }
            ]
        },
        {
            "player": {
                "id": 47370,
                "name": "Borja Bast\u00f3n",
                "firstname": "Borja",
                "lastname": "Gonz\u00e1lez Tom\u00e1s",
                "age": 31,
                "birth": {
                    "date": "1992-08-25",
                    "place": "Madrid",
                    "country": "Spain"
                },
                "nationality": "Spain",
                "height": "186 cm",
                "weight": "83 kg",
                "injured": false,
                "photo": "https://media-3.api-sports.io/football/players/47370.png"
            },
            "statistics": [
                {
                    "team": {
                        "id": 718,
                        "name": "Oviedo",
                        "logo": "https://media-2.api-sports.io/football/teams/718.png"
                    },
                    "league": {
                        "id": 141,
                        "name": "Segunda Divisi\u00f3n",
                        "country": "Spain",
                        "logo": "https://media-2.api-sports.io/football/leagues/141.png",
                        "flag": "https://media-2.api-sports.io/flags/es.svg",
                        "season": 2022
                    },
                    "games": {
                        "appearences": 33,
                        "lineups": 30,
                        "minutes": 2501,
                        "number": null,
                        "position": "Attacker",
                        "rating": "6.787500",
                        "captain": false
                    },
                    "substitutes": {
                        "in": 3,
                        "out": 9,
                        "bench": 4
                    },
                    "shots": {
                        "total": 53,
                        "on": 21
                    },
                    "goals": {
                        "total": 8,
                        "conceded": 0,
                        "assists": null,
                        "saves": null
                    },
                    "passes": {
                        "total": 603,
                        "key": 16,
                        "accuracy": 12
                    },
                    "tackles": {
                        "total": 18,
                        "blocks": 4,
                        "interceptions": 9
                    },
                    "duels": {
                        "total": 393,
                        "won": 171
                    },
                    "dribbles": {
                        "attempts": 17,
                        "success": 6,
                        "past": null
                    },
                    "fouls": {
                        "drawn": 44,
                        "committed": 50
                    },
                    "cards": {
                        "yellow": 7,
                        "yellowred": 0,
                        "red": 0
                    },
                    "penalty": {
                        "won": null,
                        "commited": null,
                        "scored": 4,
                        "missed": 1,
                        "saved": null
                    }
                }
            ]
        },
        {
            "player": {
                "id": 47395,
                "name": "Sergi Enrich",
                "firstname": "Sergi",
                "lastname": "Enrich Ametller",
                "age": 33,
                "birth": {
                    "date": "1990-02-26",
                    "place": "Ciutadella",
                    "country": "Spain"
                },
                "nationality": "Spain",
                "height": "181 cm",
                "weight": "77 kg",
                "injured": false,
                "photo": "https://media-3.api-sports.io/football/players/47395.png"
            },
            "statistics": [
                {
                    "team": {
                        "id": 718,
                        "name": "Oviedo",
                        "logo": "https://media-3.api-sports.io/football/teams/718.png"
                    },
                    "league": {
                        "id": 141,
                        "name": "Segunda Divisi\u00f3n",
                        "country": "Spain",
                        "logo": "https://media-3.api-sports.io/football/leagues/141.png",
                        "flag": "https://media-3.api-sports.io/flags/es.svg",
                        "season": 2022
                    },
                    "games": {
                        "appearences": 34,
                        "lineups": 21,
                        "minutes": 1876,
                        "number": null,
                        "position": "Attacker",
                        "rating": "6.741176",
                        "captain": false
                    },
                    "substitutes": {
                        "in": 13,
                        "out": 18,
                        "bench": 19
                    },
                    "shots": {
                        "total": 30,
                        "on": 17
                    },
                    "goals": {
                        "total": 7,
                        "conceded": 0,
                        "assists": 1,
                        "saves": null
                    },
                    "passes": {
                        "total": 526,
                        "key": 17,
                        "accuracy": 9
                    },
                    "tackles": {
                        "total": 21,
                        "blocks": 3,
                        "interceptions": 3
                    },
                    "duels": {
                        "total": 370,
                        "won": 173
                    },
                    "dribbles": {
                        "attempts": 15,
                        "success": 9,
                        "past": null
                    },
                    "fouls": {
                        "drawn": 27,
                        "committed": 38
                    },
                    "cards": {
                        "yellow": 2,
                        "yellowred": 1,
                        "red": 1
                    },
                    "penalty": {
                        "won": null,
                        "commited": null,
                        "scored": 0,
                        "missed": 0,
                        "saved": null
                    }
                }
            ]
        },
        {
            "player": {
                "id": 342340,
                "name": "Mario Fuente",
                "firstname": "Mario",
                "lastname": "Fuente Fern\u00e1ndez",
                "age": 19,
                "birth": {
                    "date": "2004-06-19",
                    "place": "Oviedo",
                    "country": "Spain"
                },
                "nationality": "Spain",
                "height": "180 cm",
                "weight": null,
                "injured": false,
                "photo": "https://media-1.api-sports.io/football/players/342340.png"
            },
            "statistics": [
                {
                    "team": {
                        "id": 718,
                        "name": "Oviedo",
                        "logo": "https://media-3.api-sports.io/football/teams/718.png"
                    },
                    "league": {
                        "id": 141,
                        "name": "Segunda Divisi\u00f3n",
                        "country": "Spain",
                        "logo": "https://media-3.api-sports.io/football/leagues/141.png",
                        "flag": "https://media-2.api-sports.io/flags/es.svg",
                        "season": 2022
                    },
                    "games": {
                        "appearences": 0,
                        "lineups": 0,
                        "minutes": 0,
                        "number": null,
                        "position": "Attacker",
                        "rating": null,
                        "captain": false
                    },
                    "substitutes": {
                        "in": 0,
                        "out": 0,
                        "bench": 2
                    },
                    "shots": {
                        "total": null,
                        "on": null
                    },
                    "goals": {
                        "total": 0,
                        "conceded": 0,
                        "assists": null,
                        "saves": null
                    },
                    "passes": {
                        "total": null,
                        "key": null,
                        "accuracy": null
                    },
                    "tackles": {
                        "total": null,
                        "blocks": null,
                        "interceptions": null
                    },
                    "duels": {
                        "total": null,
                        "won": null
                    },
                    "dribbles": {
                        "attempts": null,
                        "success": null,
                        "past": null
                    },
                    "fouls": {
                        "drawn": null,
                        "committed": null
                    },
                    "cards": {
                        "yellow": 0,
                        "yellowred": 0,
                        "red": 0
                    },
                    "penalty": {
                        "won": null,
                        "commited": null,
                        "scored": 0,
                        "missed": 0,
                        "saved": null
                    }
                }
            ]
        },
        {
            "player": {
                "id": 385396,
                "name": "Mascarenhas",
                "firstname": "Francisco",
                "lastname": "Fuma\u00e7a Mascarenhas Costa Pesso",
                "age": 23,
                "birth": {
                    "date": "2000-05-15",
                    "place": "Cascais",
                    "country": "Portugal"
                },
                "nationality": "Portugal",
                "height": "182 cm",
                "weight": "70 kg",
                "injured": false,
                "photo": "https://media-2.api-sports.io/football/players/385396.png"
            },
            "statistics": [
                {
                    "team": {
                        "id": 718,
                        "name": "Oviedo",
                        "logo": "https://media-1.api-sports.io/football/teams/718.png"
                    },
                    "league": {
                        "id": 141,
                        "name": "Segunda Divisi\u00f3n",
                        "country": "Spain",
                        "logo": "https://media-1.api-sports.io/football/leagues/141.png",
                        "flag": "https://media-2.api-sports.io/flags/es.svg",
                        "season": 2022
                    },
                    "games": {
                        "appearences": 9,
                        "lineups": 1,
                        "minutes": 169,
                        "number": null,
                        "position": "Attacker",
                        "rating": "6.512500",
                        "captain": false
                    },
                    "substitutes": {
                        "in": 8,
                        "out": 1,
                        "bench": 11
                    },
                    "shots": {
                        "total": 7,
                        "on": 3
                    },
                    "goals": {
                        "total": 1,
                        "conceded": 0,
                        "assists": null,
                        "saves": null
                    },
                    "passes": {
                        "total": 30,
                        "key": null,
                        "accuracy": 2
                    },
                    "tackles": {
                        "total": 1,
                        "blocks": null,
                        "interceptions": 1
                    },
                    "duels": {
                        "total": 57,
                        "won": 19
                    },
                    "dribbles": {
                        "attempts": 8,
                        "success": 1,
                        "past": null
                    },
                    "fouls": {
                        "drawn": 5,
                        "committed": 6
                    },
                    "cards": {
                        "yellow": 1,
                        "yellowred": 0,
                        "red": 0
                    },
                    "penalty": {
                        "won": null,
                        "commited": null,
                        "scored": 0,
                        "missed": 0,
                        "saved": null
                    }
                }
            ]
        },
        {
            "player": {
                "id": 181163,
                "name": "Enol Rodr\u00edguez",
                "firstname": "Enol",
                "lastname": "Rodr\u00edguez Heres",
                "age": 22,
                "birth": {
                    "date": "2001-07-28",
                    "place": "Cand\u00e1s",
                    "country": "Spain"
                },
                "nationality": "Spain",
                "height": "186 cm",
                "weight": "73 kg",
                "injured": false,
                "photo": "https://media-2.api-sports.io/football/players/181163.png"
            },
            "statistics": [
                {
                    "team": {
                        "id": 718,
                        "name": "Oviedo",
                        "logo": "https://media-3.api-sports.io/football/teams/718.png"
                    },
                    "league": {
                        "id": 141,
                        "name": "Segunda Divisi\u00f3n",
                        "country": "Spain",
                        "logo": "https://media-1.api-sports.io/football/leagues/141.png",
                        "flag": "https://media-2.api-sports.io/flags/es.svg",
                        "season": 2022
                    },
                    "games": {
                        "appearences": 1,
                        "lineups": 0,
                        "minutes": 44,
                        "number": null,
                        "position": "Attacker",
                        "rating": "6.200000",
                        "captain": false
                    },
                    "substitutes": {
                        "in": 1,
                        "out": 0,
                        "bench": 1
                    },
                    "shots": {
                        "total": null,
                        "on": null
                    },
                    "goals": {
                        "total": 0,
                        "conceded": 0,
                        "assists": null,
                        "saves": null
                    },
                    "passes": {
                        "total": 12,
                        "key": null,
                        "accuracy": 7
                    },
                    "tackles": {
                        "total": null,
                        "blocks": null,
                        "interceptions": null
                    },
                    "duels": {
                        "total": 8,
                        "won": 3
                    },
                    "dribbles": {
                        "attempts": null,
                        "success": null,
                        "past": null
                    },
                    "fouls": {
                        "drawn": null,
                        "committed": 1
                    },
                    "cards": {
                        "yellow": 0,
                        "yellowred": 0,
                        "red": 0
                    },
                    "penalty": {
                        "won": null,
                        "commited": null,
                        "scored": 0,
                        "missed": 0,
                        "saved": null
                    }
                }
            ]
        },
        {
            "player": {
                "id": 264470,
                "name": "Raul Moro",
                "firstname": "Raul",
                "lastname": "Moro Prescoli",
                "age": 21,
                "birth": {
                    "date": "2002-12-05",
                    "place": null,
                    "country": "Spain"
                },
                "nationality": "Spain",
                "height": "169 cm",
                "weight": null,
                "injured": false,
                "photo": "https://media-3.api-sports.io/football/players/264470.png"
            },
            "statistics": [
                {
                    "team": {
                        "id": 718,
                        "name": "Oviedo",
                        "logo": "https://media-1.api-sports.io/football/teams/718.png"
                    },
                    "league": {
                        "id": 141,
                        "name": "Segunda Divisi\u00f3n",
                        "country": "Spain",
                        "logo": "https://media-2.api-sports.io/football/leagues/141.png",
                        "flag": "https://media-2.api-sports.io/flags/es.svg",
                        "season": 2022
                    },
                    "games": {
                        "appearences": 16,
                        "lineups": 6,
                        "minutes": 560,
                        "number": null,
                        "position": "Attacker",
                        "rating": "6.533333",
                        "captain": false
                    },
                    "substitutes": {
                        "in": 10,
                        "out": 5,
                        "bench": 12
                    },
                    "shots": {
                        "total": 10,
                        "on": 3
                    },
                    "goals": {
                        "total": 0,
                        "conceded": 0,
                        "assists": 1,
                        "saves": null
                    },
                    "passes": {
                        "total": 122,
                        "key": 13,
                        "accuracy": 5
                    },
                    "tackles": {
                        "total": 6,
                        "blocks": null,
                        "interceptions": 2
                    },
                    "duels": {
                        "total": 73,
                        "won": 25
                    },
                    "dribbles": {
                        "attempts": 30,
                        "success": 13,
                        "past": null
                    },
                    "fouls": {
                        "drawn": 6,
                        "committed": 4
                    },
                    "cards": {
                        "yellow": 3,
                        "yellowred": 0,
                        "red": 0
                    },
                    "penalty": {
                        "won": null,
                        "commited": null,
                        "scored": 0,
                        "missed": 0,
                        "saved": null
                    }
                }
            ]
        }
    ]
}